dbt_profiles/__init__.py
dbt_profiles/__main__.py
dbt_profiles/cli.py
dbt_profiles/dbt_utils.py
dbt_profiles/fix_json_schema.py
dbt_profiles/json_schema_prompt.py
dbt_profiles/main.py
dbt_profiles-0.0.1.dist-info/METADATA
dbt_profiles-0.0.1.dist-info/WHEEL
dbt_profiles-0.0.1.dist-info/entry_points.txt
dbt_profiles-0.0.1.dist-info/RECORD
