Metadata-Version: 2.1
Name: dbt-profiles
Version: 0.0.1
Summary: 
Author: Alex Rudolph
Author-email: alex3rudolph@gmail.com
Requires-Python: >=3.11,<3.13
Classifier: Programming Language :: Python :: 3
Classifier: Programming Language :: Python :: 3.11
Classifier: Programming Language :: Python :: 3.12
Requires-Dist: dbt-core (>=1.6.1)
Requires-Dist: importlib (>=1.0.4,<2.0.0)
Requires-Dist: mashumaro (>=3.10,<4.0)
Requires-Dist: prompt-toolkit (==3.0.41)
Requires-Dist: py-inquirer-cli (==0.0.2)
Requires-Dist: rcheck (>=0.0.9,<0.0.10)
Requires-Dist: ruamel-yaml (>=0.18.5,<0.19.0)
